setup.py
pyehlo/__init__.py
pyehlo/pyehlo.py
pyehlo.egg-info/PKG-INFO
pyehlo.egg-info/SOURCES.txt
pyehlo.egg-info/dependency_links.txt
pyehlo.egg-info/top_level.txt