Metadata-Version: 1.0
Name: pyehlo
Version: 0.0.2
Summary: Library for sending email
Home-page: UNKNOWN
Author: UNKNOWN
Author-email: UNKNOWN
License: UNKNOWN
Platform: UNKNOWN
